vdot_calculator/__init__.py
vdot_calculator/func_module.py
vdot_calculator-0.0.0.4.dist-info/LICENSE
vdot_calculator-0.0.0.4.dist-info/METADATA
vdot_calculator-0.0.0.4.dist-info/WHEEL
vdot_calculator-0.0.0.4.dist-info/top_level.txt
vdot_calculator-0.0.0.4.dist-info/RECORD
