Metadata-Version: 2.1
Name: vdot_calculator
Version: 0.0.0.4
Summary: A compact VDOT calculator adhering to the original Daniels Running Formula book.
Author-email: Cássio Maciel Lemos <cassio.lemos@petrobras.com.br>
Project-URL: Homepage, https://github.com/CassioMaciel/Daniels_Running_Formula
Project-URL: Issues, https://github.com/CassioMaciel/Daniels_Running_Formula/issues
Keywords: Vdot,running,calculator,Daniels Running Formula,athletics
Classifier: Programming Language :: Python :: 3
Classifier: Development Status :: 1 - Planning
Classifier: License :: OSI Approved :: MIT License
Classifier: Operating System :: OS Independent
Classifier: Intended Audience :: Developers
Requires-Python: >=3.8
License-File: LICENSE
